aaiopay/__init__.py
aaiopay/api.py
aaiopay/exceptions/__init__.py
aaiopay/exceptions/errors.py
aaiopay/models/__init__.py
aaiopay/models/balance.py
aaiopay/models/order.py
aaiopay/models/withdrawal.py
aaiopay/requests.py
aaiopay-0.2.5.dist-info/METADATA
aaiopay-0.2.5.dist-info/WHEEL
aaiopay-0.2.5.dist-info/RECORD
